jupyterlab_bucket_explorer/__init__.py
jupyterlab_bucket_explorer/_version.py
jupyterlab_bucket_explorer/connection_manager.py
jupyterlab_bucket_explorer/handlers.py
jupyterlab_bucket_explorer/providers.py
jupyterlab_bucket_explorer/utils.py
jupyterlab_bucket_explorer/tests/__init__.py
jupyterlab_bucket_explorer/tests/conftest.py
jupyterlab_bucket_explorer/tests/test_api_handlers.py
jupyterlab_bucket_explorer/tests/test_auth.py
jupyterlab_bucket_explorer/tests/test_handlers.py
jupyterlab_bucket_explorer/tests/test_ops.py
jupyterlab_bucket_explorer-0.1.0.data/data/etc/jupyter/jupyter_notebook_config.d/jupyterlab-bucket-explorer.json
jupyterlab_bucket_explorer-0.1.0.data/data/etc/jupyter/jupyter_server_config.d/jupyterlab-bucket-explorer.json
jupyterlab_bucket_explorer-0.1.0.data/data/share/jupyter/labextensions/jupyterlab-bucket-explorer/package.json
jupyterlab_bucket_explorer-0.1.0.data/data/share/jupyter/labextensions/jupyterlab-bucket-explorer/schemas/jupyterlab-bucket-explorer/package.json.orig
jupyterlab_bucket_explorer-0.1.0.data/data/share/jupyter/labextensions/jupyterlab-bucket-explorer/schemas/jupyterlab-bucket-explorer/plugin.json
jupyterlab_bucket_explorer-0.1.0.data/data/share/jupyter/labextensions/jupyterlab-bucket-explorer/static/456.fea61ad052225bdde2fe.js
jupyterlab_bucket_explorer-0.1.0.data/data/share/jupyter/labextensions/jupyterlab-bucket-explorer/static/504.f3e4d8a9fca05053377c.js
jupyterlab_bucket_explorer-0.1.0.data/data/share/jupyter/labextensions/jupyterlab-bucket-explorer/static/793.ac094e4c8551f375349b.js
jupyterlab_bucket_explorer-0.1.0.data/data/share/jupyter/labextensions/jupyterlab-bucket-explorer/static/remoteEntry.15424a3136b0de27e939.js
jupyterlab_bucket_explorer-0.1.0.data/data/share/jupyter/labextensions/jupyterlab-bucket-explorer/static/style.js
jupyterlab_bucket_explorer-0.1.0.data/data/share/jupyter/labextensions/jupyterlab-bucket-explorer/static/third-party-licenses.json
jupyterlab_bucket_explorer-0.1.0.dist-info/METADATA
jupyterlab_bucket_explorer-0.1.0.dist-info/WHEEL
jupyterlab_bucket_explorer-0.1.0.dist-info/licenses/LICENSE
jupyterlab_bucket_explorer-0.1.0.dist-info/RECORD
