Metadata-Version: 2.4
Name: jupyterlab-bucket-explorer
Version: 0.1.0
Summary: Universal object storage browser for JupyterLab (S3, GCS, Azure, HDFS) by ilum
Project-URL: Homepage, https://github.com/ilum-cloud/jupyterlab-bucket-explorer
Project-URL: Repository, https://github.com/ilum-cloud/jupyterlab-bucket-explorer.git
Project-URL: Issues, https://github.com/ilum-cloud/jupyterlab-bucket-explorer/issues
Author-email: Ilum Labs LLC <support@ilum.cloud>
License:                                  Apache License
License-File: LICENSE
Keywords: AWS,Azure,Azure Blob Storage,Bucket Explorer,Cloud Storage,File Browser,GCS,Google Cloud Storage,HDFS,Hadoop,Jupyter,JupyterLab,JupyterLab4,MinIO,Multi Cloud,Object Storage,S3,jupyterlab-extension
Classifier: Framework :: Jupyter
Classifier: Framework :: Jupyter :: JupyterLab
Classifier: Framework :: Jupyter :: JupyterLab :: 4
Classifier: Framework :: Jupyter :: JupyterLab :: Extensions
Classifier: Framework :: Jupyter :: JupyterLab :: Extensions :: Prebuilt
Classifier: License :: OSI Approved :: Apache Software License
Classifier: Programming Language :: Python
Classifier: Programming Language :: Python :: 3
Classifier: Programming Language :: Python :: 3.8
Classifier: Programming Language :: Python :: 3.9
Classifier: Programming Language :: Python :: 3.10
Classifier: Programming Language :: Python :: 3.11
Classifier: Programming Language :: Python :: 3.12
Requires-Python: >=3.8
Requires-Dist: boto3
Requires-Dist: colorlog
Requires-Dist: jupyter-server>=2.0.0
Requires-Dist: jupyterlab<5,>=4.0.0
Requires-Dist: s3fs>=2021.10.1
Requires-Dist: singleton-decorator
Provides-Extra: dev
Requires-Dist: coverage; extra == 'dev'
Requires-Dist: moto[s3]; extra == 'dev'
Requires-Dist: pytest; extra == 'dev'
Requires-Dist: pytest-asyncio; extra == 'dev'
Requires-Dist: pytest-cov; extra == 'dev'
Requires-Dist: pytest-jupyter; extra == 'dev'
Requires-Dist: pytest-tornasync; extra == 'dev'
Requires-Dist: ruff; extra == 'dev'
Provides-Extra: test
Requires-Dist: coverage; extra == 'test'
Requires-Dist: moto[s3]; extra == 'test'
Requires-Dist: pytest; extra == 'test'
Requires-Dist: pytest-asyncio; extra == 'test'
Requires-Dist: pytest-cov; extra == 'test'
Requires-Dist: pytest-jupyter; extra == 'test'
Requires-Dist: pytest-tornasync; extra == 'test'
Requires-Dist: ruff; extra == 'test'
